MANIFEST.in
README.md
setup.py
pytakt/LICENSE.txt
pytakt/__init__.py
pytakt/_version.py
pytakt/chord.py
pytakt/constants.py
pytakt/context.py
pytakt/effector.py
pytakt/event.py
pytakt/frameutils.py
pytakt/interpolator.py
pytakt/m21conv.py
pytakt/midiio.py
pytakt/mml.py
pytakt/mml_evalexp.py
pytakt/pianoroll.py
pytakt/pitch.py
pytakt/pmconv.py
pytakt/pytaktcmd.py
pytakt/sc.py
pytakt/scale.py
pytakt/score.py
pytakt/smf.py
pytakt/text.py
pytakt/timemap.py
pytakt/utils.py
pytakt.egg-info/PKG-INFO
pytakt.egg-info/SOURCES.txt
pytakt.egg-info/dependency_links.txt
pytakt.egg-info/entry_points.txt
pytakt.egg-info/requires.txt
pytakt.egg-info/top_level.txt
pytakt/gm/__init__.py
pytakt/gm/drums.py
pytakt/src/Makefile
pytakt/src/_cstddefs.h
pytakt/src/cmidiio.cpp
pytakt/src/defs.h
pytakt/src/midiin.cpp
pytakt/src/midiin.h
pytakt/src/midiout.cpp
pytakt/src/midiout.h
pytakt/src/notemap.h
pytakt/src/sysdep.cpp
pytakt/src/sysdep.h
pytakt/src/sysdepGeneric.cpp
pytakt/src/sysdepGeneric.h
pytakt/src/sysdepLinux.cpp
pytakt/src/sysdepLinux.h
pytakt/src/sysdepMacOSX.cpp
pytakt/src/sysdepMacOSX.h
pytakt/src/sysdepWin.cpp
pytakt/src/sysdepWin.h
pytakt/src/takterror.h