Metadata-Version: 2.1
Name: pytakt
Version: 1.0.0
Summary: A Python library for music description, generation, and processing with realtime MIDI I/O
Home-page: http://github.com/snisim/pytakt/
Author: Satoshi Nishimura
Author-email: nisim@u-aizu.ac.jp
License: BSD-3-Clause
Keywords: MIDI,standard MIDI files,MML,algorithmic composition
Classifier: Development Status :: 4 - Beta
Classifier: License :: OSI Approved :: BSD License
Classifier: Operating System :: MacOS :: MacOS X
Classifier: Operating System :: Microsoft :: Windows
Classifier: Operating System :: POSIX :: Linux
Classifier: Topic :: Multimedia :: Sound/Audio :: MIDI
Requires-Python: >=3.6
Requires-Dist: Arpeggio>=1.9
